Metadata-Version: 1.2
Name: ssd-checker
Version: 1.0.3
Summary: Solid-state drive (ssd) checker
Home-page: https://github.com/kipodd/ssd_checker
Author: kipodd
License: MIT
Download-URL: https://github.com/kipodd/ssd_checker/releases
Keywords: ssd check checker solid state drive pyssd
Platform: any
Classifier: Development Status :: 5 - Production/Stable
Classifier: Intended Audience :: Developers
Classifier: Intended Audience :: End Users/Desktop
Classifier: License :: OSI Approved :: MIT License
Classifier: Natural Language :: English
Classifier: Operating System :: MacOS :: MacOS X
Classifier: Operating System :: Microsoft :: Windows
Classifier: Operating System :: POSIX
Classifier: Programming Language :: Python
Classifier: Programming Language :: Python :: 2
Classifier: Programming Language :: Python :: 2.6
Classifier: Programming Language :: Python :: 2.7
Classifier: Programming Language :: Python :: 3
Classifier: Programming Language :: Python :: 3.3
Classifier: Programming Language :: Python :: 3.4
Classifier: Programming Language :: Python :: 3.5
Classifier: Programming Language :: Python :: 3.6
Classifier: Topic :: Software Development :: Libraries :: Python Modules
Classifier: Topic :: System
Classifier: Topic :: System :: Filesystems
Classifier: Topic :: Utilities
Requires-Python: >=2.6,!=3.0,!=3.1,!=3.2
